forkit/__init__.py
forkit/commit.py
forkit/diff.py
forkit/fork.py
forkit/models.py
forkit/reset.py
forkit/signals.py
forkit/tools.py
forkit/utils.py
forkit_django-0.10.1.dist-info/LICENSE
forkit_django-0.10.1.dist-info/METADATA
forkit_django-0.10.1.dist-info/WHEEL
forkit_django-0.10.1.dist-info/top_level.txt
forkit_django-0.10.1.dist-info/RECORD
